LICENSE
MANIFEST.in
README.md
setup.py
javasphinx/__init__.py
javasphinx/apidoc.py
javasphinx/compiler.py
javasphinx/domain.py
javasphinx/extdoc.py
javasphinx/formatter.py
javasphinx/htmlrst.py
javasphinx/util.py
javasphinx_workaround.egg-info/PKG-INFO
javasphinx_workaround.egg-info/SOURCES.txt
javasphinx_workaround.egg-info/dependency_links.txt
javasphinx_workaround.egg-info/entry_points.txt
javasphinx_workaround.egg-info/requires.txt
javasphinx_workaround.egg-info/top_level.txt